molselector/__init__.py
molselector/app.py
molselector/cli.py
molselector/static/app.js
molselector/static/styles.css
molselector/templates/index.html
molselector-1.2.0.dist-info/licenses/LICENSE
molselector-1.2.0.dist-info/METADATA
molselector-1.2.0.dist-info/WHEEL
molselector-1.2.0.dist-info/entry_points.txt
molselector-1.2.0.dist-info/top_level.txt
molselector-1.2.0.dist-info/RECORD
