Metadata-Version: 2.4
Name: molselector
Version: 1.2.0
Summary: A web app to quickly triage molecule files.
Requires-Python: >=3.12
License-File: LICENSE
Requires-Dist: fastapi>=0.110.0
Requires-Dist: jinja2>=3.1.0
Requires-Dist: uvicorn[standard]>=0.27.0
Requires-Dist: typer>=0.12.3
Dynamic: license-file
